README
setup.py
IXOpenIDClient.egg-info/PKG-INFO
IXOpenIDClient.egg-info/SOURCES.txt
IXOpenIDClient.egg-info/dependency_links.txt
IXOpenIDClient.egg-info/requires.txt
IXOpenIDClient.egg-info/top_level.txt
ixopenid_client/__init__.py
ixopenid_client/admin.py
ixopenid_client/forms.py
ixopenid_client/models.py