Metadata-Version: 1.0
Name: IXOpenIDClient
Version: 0.1.0
Summary: OpenID Client for applications using IX Profile servers
Home-page: http://pypi.python.org/pypi/IXOpenIDClient/
Author: Infoxchanhe Australia dev team
Author-email: devs@infoxchange.net.au
License: MIT
Platform: UNKNOWN
